ossbomer_schema/__init__.py
ossbomer_schema/cli.py
ossbomer_schema/validator.py
ossbomer_schema-1.2.1.dist-info/LICENSE
ossbomer_schema-1.2.1.dist-info/METADATA
ossbomer_schema-1.2.1.dist-info/WHEEL
ossbomer_schema-1.2.1.dist-info/entry_points.txt
ossbomer_schema-1.2.1.dist-info/top_level.txt
ossbomer_schema-1.2.1.dist-info/RECORD
